search_and_replace/__init__.py
search_and_replace/diff_apply.py
search_and_replace/main.py
tests/__init__.py
tests/test_diff_apply.py
search_and_replace-0.2.2.dist-info/METADATA
search_and_replace-0.2.2.dist-info/WHEEL
search_and_replace-0.2.2.dist-info/entry_points.txt
search_and_replace-0.2.2.dist-info/top_level.txt
search_and_replace-0.2.2.dist-info/RECORD
